__init__.py
wake_build/__init__.py
wake_build/__main__.py
wake_build/config.py
wake_build/docker.py
wake_build/exc.py
wake_build/log.py
wake_build/util.py
wake_build/wake.py
wake_build-0.2.5.dist-info/licenses/LICENSE
wake_build-0.2.5.dist-info/METADATA
wake_build-0.2.5.dist-info/WHEEL
wake_build-0.2.5.dist-info/entry_points.txt
wake_build-0.2.5.dist-info/top_level.txt
wake_build-0.2.5.dist-info/RECORD
