Metadata-Version: 2.4
Name: wake-build
Version: 0.2.5
Summary: Wake container build orchestrator
Classifier: Programming Language :: Python :: 3
Requires-Python: >=3.7
License-File: LICENSE
Requires-Dist: pyyaml
Requires-Dist: tqdm
Requires-Dist: python-dotenv
Dynamic: license-file
